{
	"id": "3b9907duu",
	"name": "hello",
	"serviceId": "hello",
	"nodeList": [
		{
			"id": "c4nc6dtiab",
			"name": "开始节点",
			"type": "start",
			"left": "186px",
			"top": "49px",
			"ico": "el-icon-time"
		},
		{
			"id": "s2o6dot0sn",
			"name": "结束节点",
			"type": "end",
			"left": "279px",
			"top": "551px",
			"ico": "el-icon-time"
		},
		{
			"id": "u3sspcmlkd",
			"name": "http请求节点",
			"type": "http",
			"left": "198px",
			"top": "135px",
			"ico": "el-icon-odometer",
			"url": "http://localhost:8080/world",
			"resultName": "baiduResult"
		},
		{
			"id": "u70yn0bp89",
			"name": "http请求节点1",
			"type": "http",
			"left": "448px",
			"top": "207px",
			"ico": "el-icon-odometer",
			"url": "http://localhost:8080/hello",
			"resultName": "localResult"
		},
		{
			"id": "bjzsk2a5d",
			"name": "json转换节点",
			"type": "jsonTransform",
			"left": "367px",
			"top": "264px",
			"ico": "el-icon-odometer",
			"transformFrom": "baiduResult",
			"transformTo": "br"
		},
		{
			"id": "lvlhimidro",
			"name": "json转换节点1",
			"type": "jsonTransform",
			"left": "481px",
			"top": "388px",
			"ico": "el-icon-odometer",
			"transformFrom": "localResult",
			"transformTo": "lr"
		},
		{
			"id": "3krvtqnsh",
			"name": "结果响应节点",
			"type": "result",
			"left": "195px",
			"top": "440px",
			"ico": "el-icon-odometer",
			"template": "{\"first\": \"${br[\"serviceId\"]}\", \"second\": \"${lr[\"serviceId\"]}\"}"
		}
	],
	"lineList": [
		{
			"from": "c4nc6dtiab",
			"to": "u3sspcmlkd",
			"type": "direct"
		},
		{
			"from": "3krvtqnsh",
			"to": "s2o6dot0sn",
			"type": "direct"
		},
		{
			"from": "u3sspcmlkd",
			"to": "u70yn0bp89",
			"type": "direct"
		},
		{
			"from": "u70yn0bp89",
			"to": "bjzsk2a5d",
			"type": "direct"
		},
		{
			"from": "bjzsk2a5d",
			"to": "lvlhimidro",
			"type": "direct"
		},
		{
			"from": "lvlhimidro",
			"to": "3krvtqnsh",
			"type": "direct"
		}
	]
}
